bycore/__init__.py
bycore/cipher.py
bycore/generate.py
bycore/hashing.py
bycore/managers.py
bycore/models.py
bycore/storage.py
bycore-0.0.1.dist-info/LICENSE
bycore-0.0.1.dist-info/METADATA
bycore-0.0.1.dist-info/WHEEL
bycore-0.0.1.dist-info/top_level.txt
bycore-0.0.1.dist-info/RECORD
