Metadata-Version: 2.1
Name: bycore
Version: 0.0.1
Summary: Bypass Core package
Home-page: https://github.com/masterr314/bycore
Author: master
Author-email: masterrr314@gmail.com
Project-URL: Bug Tracker, https://github.com/masterr314/bycore/issues
Classifier: Programming Language :: Python :: 3
Classifier: License :: OSI Approved :: MIT License
Classifier: Operating System :: OS Independent
Requires-Python: >=3.9.7
License-File: LICENSE
